{
  "db_name": "PostgreSQL",
  "query": "\n        SELECT COUNT(*) as \"count!\"\n        FROM webhook_deliveries\n        WHERE webhook_id = $1\n          AND ($2::boolean IS NULL OR success = $2)\n        ",
  "describe": {
    "columns": [
      {
        "ordinal": 0,
        "name": "count!",
        "type_info": "Int8"
      }
    ],
    "parameters": {
      "Left": [
        "Uuid",
        "Bool"
      ]
    },
    "nullable": [
      null
    ]
  },
  "hash": "378c5f494301e55a74fbb0618b1e75f994678caea067b1eb2b77a0124135ec64"
}
